qass/tools/analyzer/__init__.py
qass/tools/analyzer/buffer_metadata_cache.py
qass/tools/analyzer/buffer_parser.py
qass/tools/analyzer/database_model.py
qass/tools/analyzer/deleting_process.py
qass/tools/analyzer/input_observer.py
qass/tools/analyzer/mainthread_hook.py
qass/tools/analyzer/search_indicator.py
qass/tools/analyzer/testing.py
qass/tools/analyzer/virtual_devices.py
qass/tools/analyzer/tests/test_buffer_metadata_cache.py
qass/tools/analyzer/tests/test_buffer_parser.py
qass/tools/analyzer/tests/test_deleting_process.py
qass_tools_analyzer-2.6.3.dist-info/licenses/COPYING
qass_tools_analyzer-2.6.3.dist-info/licenses/COPYING.LESSER
qass_tools_analyzer-2.6.3.dist-info/METADATA
qass_tools_analyzer-2.6.3.dist-info/WHEEL
qass_tools_analyzer-2.6.3.dist-info/top_level.txt
qass_tools_analyzer-2.6.3.dist-info/RECORD
