Metadata-Version: 2.4
Name: qass-tools-analyzer
Version: 2.6.3
Summary: Analyzer package for qass_tools
Author-email: Nicklas Osmers <nosmers@qass.net>
Project-URL: Homepage, https://github.com/QASS/qass-tools-analyzer
Classifier: Programming Language :: Python :: 3
Classifier: License :: OSI Approved :: GNU Lesser General Public License v3 (LGPLv3)
Classifier: Operating System :: OS Independent
Requires-Python: >=3.6
License-File: COPYING
License-File: COPYING.LESSER
Requires-Dist: SQLAlchemy>=1.4.36
Requires-Dist: tqdm>=4.64.0
Requires-Dist: Deprecated>=1.2.13
Requires-Dist: numpy>=1.19.5
Requires-Dist: pandas>=1.1.5
Requires-Dist: mysql-connector-python
Requires-Dist: pymysql
Provides-Extra: test
Requires-Dist: pytest; extra == "test"
Requires-Dist: pytest-cov; extra == "test"
Requires-Dist: pytest-pretty; extra == "test"
Provides-Extra: docs
Requires-Dist: sphinx; extra == "docs"
Requires-Dist: sphinx_rtd_theme; extra == "docs"
Dynamic: license-file
